pylingva/__init__.py
pylingva/arg.py
pylingva/cli.py
pylingva/pylingva.py
pylingva-0.1.2.dist-info/LICENSE
pylingva-0.1.2.dist-info/METADATA
pylingva-0.1.2.dist-info/WHEEL
pylingva-0.1.2.dist-info/entry_points.txt
pylingva-0.1.2.dist-info/top_level.txt
pylingva-0.1.2.dist-info/RECORD
