Metadata-Version: 2.1
Name: pylingva
Version: 0.1.2
Summary: Simple translator using Lingva Translate API
Home-page: https://gitlab.com/nesstero/pylingva
Author: nestero
Author-email: nestero@mail.com
License: MIT
Platform: UNKNOWN
License-File: LICENSE
